trood/__init__.py
trood/api/__init__.py
trood/api/custodian/__init__.py
trood/api/custodian/client.py
trood/api/custodian/command.py
trood/api/custodian/exceptions.py
trood/api/custodian/records/__init__.py
trood/api/custodian/records/manager.py
trood/api/custodian/records/model.py
trood/api/custodian/records/query.py
trood/api/custodian/tests/__init__.py
trood/api/custodian/tests/conftest.py
trood/api/custodian/tests/test_operations.py
trood/api/custodian/tests/test_partial_update.py
trood/api/custodian/tests/test_query.py
trood/api/custodian/tests/test_rql.py
trood/contrib/__init__.py
trood/contrib/django/__init__.py
trood/contrib/django/filters.py
trood/contrib/django/pagination.py
trood/contrib/django/serializers.py
trood/contrib/django/apps/__init__.py
trood/contrib/django/apps/fixtures/__init__.py
trood/contrib/django/apps/fixtures/urls.py
trood/contrib/django/apps/fixtures/views.py
trood/contrib/django/apps/meta/__init__.py
trood/contrib/django/apps/meta/views.py
trood/contrib/django/apps/plugins/__init__.py
trood/contrib/django/apps/plugins/apps.py
trood/contrib/django/apps/plugins/core.py
trood/contrib/django/apps/plugins/models.py
trood/contrib/django/apps/plugins/serialiers.py
trood/contrib/django/apps/plugins/urls.py
trood/contrib/django/apps/plugins/views.py
trood/contrib/django/apps/plugins/migrations/0001_initial.py
trood/contrib/django/apps/plugins/migrations/__init__.py
trood/contrib/django/auth/__init__.py
trood/contrib/django/auth/authentication.py
trood/contrib/django/auth/engine.py
trood/contrib/django/auth/filter.py
trood/contrib/django/auth/middleware.py
trood/contrib/django/auth/permissions.py
trood/contrib/django/auth/renderers.py
trood/contrib/django/mail/__init__.py
trood/contrib/django/mail/backends.py
trood/contrib/django/tests/__init__.py
trood/contrib/django/tests/settings.py
trood/contrib/django/tests/test_abac_permissions.py
trood/contrib/django/tests/test_meta.py
trood/contrib/django/tests/test_renderer.py
trood-1.0.7.dist-info/METADATA
trood-1.0.7.dist-info/WHEEL
trood-1.0.7.dist-info/top_level.txt
trood-1.0.7.dist-info/RECORD
