Metadata-Version: 2.1
Name: trood
Version: 1.0.7
Summary: UNKNOWN
Home-page: UNKNOWN
Author: Trood Inc
License: UNKNOWN
Platform: UNKNOWN
Requires-Dist: requests (==2.22.0)
Requires-Dist: djangorestframework
Requires-Dist: django
Requires-Dist: pyparsing
Requires-Dist: dateparser
Requires-Dist: django-redis
